structured_data_profiling/__init__.py
structured_data_profiling/data_slicing/__init__.py
structured_data_profiling/data_slicing/data_slicing.py
structured_data_profiling/data_tests/__init__.py
structured_data_profiling/data_tests/data_tests.py
structured_data_profiling/data_tests/temporal_test.py
structured_data_profiling/expectations/__init__.py
structured_data_profiling/expectations/great_expectations.py
structured_data_profiling/preprocessor/__init__.py
structured_data_profiling/preprocessor/preprocessor.py
structured_data_profiling/profiler/__init__.py
structured_data_profiling/profiler/multitable.py
structured_data_profiling/profiler/profiler.py
structured_data_profiling/utils/__init__.py
structured_data_profiling/utils/utils.py
structured_profiling-0.3.11.dist-info/LICENSE
structured_profiling-0.3.11.dist-info/METADATA
structured_profiling-0.3.11.dist-info/WHEEL
structured_profiling-0.3.11.dist-info/RECORD
