Metadata-Version: 2.1
Name: structured-profiling
Version: 0.3.11
Summary: A Python library to check for data quality and automatically generate data tests. 
Home-page: https://github.com/Clearbox-AI/StructuredDataProfiling
License: GPL
Author: Clearbox AI
Author-email: info@clearbox.ai
Requires-Python: >=3.9,<3.13
Classifier: License :: Other/Proprietary License
Classifier: Programming Language :: Python :: 3
Classifier: Programming Language :: Python :: 3.9
Classifier: Programming Language :: Python :: 3.10
Classifier: Programming Language :: Python :: 3.11
Requires-Dist: dateparser (>=1,<2)
Requires-Dist: distfit (>=1.4,<2.0)
Requires-Dist: great-expectations (>=0.15)
Requires-Dist: numpy (>1.23.3)
Requires-Dist: pandas (>=1.5.2)
Requires-Dist: scikit-learn (>=1.1.3)
Requires-Dist: scipy (>=1.9.3)
Project-URL: Repository, https://github.com/Clearbox-AI/StructuredDataProfiling
